DbH/__init__.py
DbH/main.py
DbH-0.0.1.dist-info/METADATA
DbH-0.0.1.dist-info/WHEEL
DbH-0.0.1.dist-info/top_level.txt
DbH-0.0.1.dist-info/RECORD
