Metadata-Version: 2.1
Name: DbH
Version: 0.0.1
Summary: A library that facilitates working with databases
Home-page: UNKNOWN
Author: Kaliyev Arsen
Author-email: kaliyev.arsen@gmail.com
License: UNKNOWN
Keywords: python,databases,sqlite3,efficiency
Platform: UNKNOWN
Classifier: Development Status :: 5 - Production/Stable
Classifier: Intended Audience :: Developers
Classifier: Programming Language :: Python :: 3
Classifier: Operating System :: Unix
Classifier: Operating System :: MacOS :: MacOS X
Classifier: Operating System :: Microsoft :: Windows
